README.txt
setup.py
src/fabric/__init__.py
src/fabric.buildout_recipe.egg-info/PKG-INFO
src/fabric.buildout_recipe.egg-info/SOURCES.txt
src/fabric.buildout_recipe.egg-info/dependency_links.txt
src/fabric.buildout_recipe.egg-info/entry_points.txt
src/fabric.buildout_recipe.egg-info/namespace_packages.txt
src/fabric.buildout_recipe.egg-info/not-zip-safe
src/fabric.buildout_recipe.egg-info/requires.txt
src/fabric.buildout_recipe.egg-info/top_level.txt
src/fabric/buildout_recipe/__init__.py