Metadata-Version: 1.0
Name: fabric.buildout-recipe
Version: 0.1
Summary: Recipe base for writing fabric-buildout recipe.
Home-page: https://bitbucket.org/imagawa_yakata/fabric.buildout-recipe
Author: Imagawa Yakata
Author-email: imagawa.yakata@gmail.com
License: gpl
Keywords: Fabric Buildout Deploy
Platform: UNKNOWN
Classifier: Programming Language :: Python
